mitocyto/__init__.py
mitocyto/detectfibres.py
mitocyto/gui.py
mitocyto/gui2.py
mitocyto/version.py
mitocyto-0.0.10.dist-info/METADATA
mitocyto-0.0.10.dist-info/RECORD
mitocyto-0.0.10.dist-info/WHEEL
mitocyto-0.0.10.dist-info/entry_points.txt
mitocyto-0.0.10.dist-info/top_level.txt
mitocyto_scripts/__init__.py
mitocyto_scripts/auto.py
mitocyto_scripts/getResults.py
mitocyto_scripts/gui.py
mitocyto_scripts/mitocytoAllTheThings.py
mitocyto_scripts/tagFiles.py
scripts/__init__.py
scripts/auto.py
scripts/getResults.py
scripts/gui.py
scripts/gui2.py
scripts/tagFiles.py
