Metadata-Version: 2.1
Name: mitocyto
Version: 0.0.10
Summary: Image analysis of cells in serial sections
Home-page: http://cnr.lwlss.net
Author: Conor Lawless
Author-email: cnr.lwlss@gmail.com
License: UNKNOWN
Platform: UNKNOWN
Classifier: Development Status :: 3 - Alpha
Classifier: Topic :: Scientific/Engineering :: Image Recognition
Classifier: Intended Audience :: Science/Research
Requires-Dist: psutil
Requires-Dist: numpy
Requires-Dist: scipy
Requires-Dist: pandas
Requires-Dist: pillow
Requires-Dist: opencv-python
Requires-Dist: matplotlib
Requires-Dist: scikit-image
